xface/__init__.py
xface/face_analysis.py
xface/core/__init__.py
xface/core/image_cropper.py
xface/core/utils.py
xface/model/__init__.py
xface/model/base.py
xface/model/face_alignment.py
xface/model/face_detection.py
xface/model/face_recognition.py
xface/models/face_alignment/face_alignment_1.0/face_landmark_pfld.pkl
xface/models/face_alignment/face_alignment_1.0/model_meta.json
xface/models/face_alignment/face_alignment_2.0/face_landmark_pfld.pkl
xface/models/face_alignment/face_alignment_2.0/model_meta.json
xface/models/face_detection/face_detection_1.0/face_detection_retina.pkl
xface/models/face_detection/face_detection_1.0/model_meta.json
xface/models/face_detection/face_detection_2.0/face_detection_retina.pkl
xface/models/face_detection/face_detection_2.0/model_meta.json
xface/models/face_recognition/face_recognition_1.0/face_recognition_mv.pkl
xface/models/face_recognition/face_recognition_1.0/model_meta.json
xface/models/face_recognition/face_recognition_2.0/face_recognition_mv.pkl
xface/models/face_recognition/face_recognition_2.0/model_meta.json
xface/models/network_def/mobilefacenet_def.py
xface/models/network_def/mobilev3_pfld.py
xface/models/network_def/retinaface_def.py
xface-0.1.0.dist-info/LICENSE
xface-0.1.0.dist-info/METADATA
xface-0.1.0.dist-info/WHEEL
xface-0.1.0.dist-info/top_level.txt
xface-0.1.0.dist-info/RECORD
