Metadata-Version: 2.1
Name: xface
Version: 0.1.0
Summary: XFace.
Home-page: https://github.com/007gzs/xface
Author: 007
Author-email: 007gzs@gmail.com
License: MIT
Platform: UNKNOWN
Classifier: Programming Language :: Python
Classifier: Programming Language :: Python :: 3
Classifier: Programming Language :: Python :: 3 :: Only
Classifier: Programming Language :: Python :: 3.6
Classifier: Programming Language :: Python :: 3.7
Classifier: Programming Language :: Python :: 3.8
Classifier: Programming Language :: Python :: 3.9
Requires-Python: >=3.6
Requires-Dist: opencv-python
Requires-Dist: scikit-image
Requires-Dist: torch (>=1.1.0)
Requires-Dist: torchvision (>=0.3.0)
